target_mssql/__init__.py
target_mssql/connector.py
target_mssql/sinks.py
target_mssql/target.py
target_mssql/tests/__init__.py
target_mssql/tests/data_files/array_data.singer
target_mssql/tests/data_files/camelcase.singer
target_mssql/tests/data_files/camelcase_complex_schema.singer
target_mssql/tests/data_files/column_comments.singer
target_mssql/tests/data_files/disappearing_columns.singer
target_mssql/tests/data_files/duplicate_records.singer
target_mssql/tests/data_files/encoded_strings.singer
target_mssql/tests/data_files/insert_merge_part1.singer
target_mssql/tests/data_files/insert_merge_part2.singer
target_mssql/tests/data_files/invalid_schema.singer
target_mssql/tests/data_files/large_int.singer
target_mssql/tests/data_files/long_string.singer
target_mssql/tests/data_files/missing_value.singer
target_mssql/tests/data_files/multiple_state_messages.singer
target_mssql/tests/data_files/no_primary_keys.singer
target_mssql/tests/data_files/no_primary_keys_append.singer
target_mssql/tests/data_files/null_key.singer
target_mssql/tests/data_files/optional_attributes.singer
target_mssql/tests/data_files/record_before_schema.singer
target_mssql/tests/data_files/record_missing_key_property.singer
target_mssql/tests/data_files/record_missing_required_property.singer
target_mssql/tests/data_files/schema_no_properties.singer
target_mssql/tests/data_files/schema_updates.singer
target_mssql/tests/data_files/simple_continents.singer
target_mssql/tests/data_files/simple_countries.singer
target_mssql/tests/data_files/simple_stream.singer
target_mssql/tests/data_files/special_chars_in_attributes.singer
target_mssql/tests/data_files/tap_aapl.singer
target_mssql/tests/data_files/tap_countries.singer
target_mssql/tests/data_files/target_schema.singer
target_mssql/tests/data_files/user_location_data.singer
target_mssql/tests/data_files/user_location_upsert_data.singer
target_mssql/tests/samples/__init__.py
target_mssql/tests/samples/aapl/AAPL.json
target_mssql-0.2.1.dist-info/LICENSE
target_mssql-0.2.1.dist-info/METADATA
target_mssql-0.2.1.dist-info/WHEEL
target_mssql-0.2.1.dist-info/entry_points.txt
target_mssql-0.2.1.dist-info/RECORD
