Metadata-Version: 2.1
Name: target-mssql
Version: 0.2.1
Summary: `target-mssql` is a Singer target for mssql, built with the Meltano SDK for Singer Targets.
License: Apache 2.0
Keywords: ELT,mssql
Author: Henning Holgersen
Requires-Python: >=3.7.1,<3.11
Classifier: License :: Other/Proprietary License
Classifier: Programming Language :: Python :: 3
Classifier: Programming Language :: Python :: 3.8
Classifier: Programming Language :: Python :: 3.9
Classifier: Programming Language :: Python :: 3.10
Requires-Dist: pymssql (>=2.2.5)
Requires-Dist: requests (>=2.25.1,<3.0.0)
Requires-Dist: singer-sdk (==0.13.0)
